[
    {
        "name": "Mystic 1 Weapon",
        "value": 2324
    },
    {
        "name": "Mystic 1 Hat",
        "value": 2324
    },
    {
        "name": "Mystic 1 Face",
        "value": 2324
    },
    {
        "name": "Crystal 4 Ring",
        "value": 1513
    },
    {
        "name": "Dragons",
        "value": 1980
    },
    {
        "name": "Banner",
        "value": 350
    },
    {
        "name": "Flask",
        "value": 50
    },
    {
        "name": "Emblem 1",
        "value": 50
    },
    {
        "name": "Emblem 2",
        "value": 50
    },
    {
        "name": "Ally",
        "value": 75
    },
    {
        "name": "Crystal Gems",
        "value": 34892
    },
    {
        "name": "Geode Mastery",
        "value": 500
    },
    {
        "name": "Class level 30",
        "value": 450
    },
    {
        "name": "Subclass level 30",
        "value": 90
    }
]